imaxt_multiscale_plugin/__init__.py
imaxt_multiscale_plugin/_reader.py
imaxt_multiscale_plugin/_sample_data.py
imaxt_multiscale_plugin/_widget.py
imaxt_multiscale_plugin/_writer.py
imaxt_multiscale_plugin/napari.yaml
imaxt_multiscale_plugin/s3.py
imaxt_multiscale_plugin/utils.py
imaxt_multiscale_plugin/_tests/__init__.py
imaxt_multiscale_plugin/_tests/test_reader.py
imaxt_multiscale_plugin/_tests/test_sample_data.py
imaxt_multiscale_plugin/_tests/test_widget.py
imaxt_multiscale_plugin/_tests/test_writer.py
imaxt_multiscale_plugin-0.3.1.dist-info/LICENSE
imaxt_multiscale_plugin-0.3.1.dist-info/METADATA
imaxt_multiscale_plugin-0.3.1.dist-info/WHEEL
imaxt_multiscale_plugin-0.3.1.dist-info/entry_points.txt
imaxt_multiscale_plugin-0.3.1.dist-info/top_level.txt
imaxt_multiscale_plugin-0.3.1.dist-info/RECORD
