Metadata-Version: 2.1
Name: imaxt-multiscale-plugin
Version: 0.3.1
Summary: A simple plugin to use with napari
Home-page: https://gitlab.developers.cam.ac.uk/astronomy/camcead/imaxt/imaxt-multiscale-plugin
Author: Eduardo Gonzalez Solares
Author-email: E.GonzalezSolares@ast.cam.ac.uk
License: LGPL-3.0-only
Classifier: Development Status :: 2 - Pre-Alpha
Classifier: Framework :: napari
Classifier: Intended Audience :: Developers
Classifier: License :: OSI Approved :: GNU Lesser General Public License v3 (LGPLv3)
Classifier: Operating System :: OS Independent
Classifier: Programming Language :: Python
Classifier: Programming Language :: Python :: 3
Classifier: Programming Language :: Python :: 3 :: Only
Classifier: Programming Language :: Python :: 3.8
Classifier: Programming Language :: Python :: 3.9
Classifier: Programming Language :: Python :: 3.10
Classifier: Topic :: Software Development :: Testing
Requires-Python: >=3.8
License-File: LICENSE
Requires-Dist: numpy
Requires-Dist: magicgui
Requires-Dist: qtpy
Requires-Dist: xarray
Requires-Dist: dask
Requires-Dist: astropy
Requires-Dist: zarr
Provides-Extra: testing
Requires-Dist: tox ; extra == 'testing'
Requires-Dist: pytest ; extra == 'testing'
Requires-Dist: pytest-cov ; extra == 'testing'
Requires-Dist: pytest-qt ; extra == 'testing'
Requires-Dist: napari ; extra == 'testing'
Requires-Dist: pyqt5 ; extra == 'testing'
